easy_modal/__init__.py
easy_modal/gui.py
easy_modal/tui.py
easy_modal-1.0.0.dist-info/licenses/LICENSE
easy_modal-1.0.0.dist-info/METADATA
easy_modal-1.0.0.dist-info/WHEEL
easy_modal-1.0.0.dist-info/top_level.txt
easy_modal-1.0.0.dist-info/RECORD
