Metadata-Version: 2.4
Name: easy-modal
Version: 1.0.0
Summary: A library for easily implementing dialog boxes and file pickers.
Author-email: Keisuke Magara <61485115+kei-mag@users.noreply.github.com>
License: MIT License
Project-URL: Source, https://github.com/kei-mag/python-easy-modal
Keywords: dialog box,file picker,modal,gui,tui,cui,tkinter
Classifier: Programming Language :: Python :: 3
Requires-Python: >=3.9
License-File: LICENSE
Dynamic: license-file
